texsmith/__init__.py
texsmith/devtools.py
texsmith/index.py
texsmith/progressbar.py
texsmith/quotes.py
texsmith/smart_dashes.py
texsmith/texlogos.py
texsmith/adapters/__init__.py
texsmith/adapters/docker.py
texsmith/adapters/handlers/__init__.py
texsmith/adapters/handlers/_assets.py
texsmith/adapters/handlers/_helpers.py
texsmith/adapters/handlers/_mermaid.py
texsmith/adapters/handlers/admonitions.py
texsmith/adapters/handlers/basic.py
texsmith/adapters/handlers/blocks.py
texsmith/adapters/handlers/code.py
texsmith/adapters/handlers/inline.py
texsmith/adapters/handlers/links.py
texsmith/adapters/handlers/media.py
texsmith/adapters/latex/__init__.py
texsmith/adapters/latex/formatter.py
texsmith/adapters/latex/latexmk.py
texsmith/adapters/latex/pygments.py
texsmith/adapters/latex/pyxindy.py
texsmith/adapters/latex/renderer.py
texsmith/adapters/latex/tectonic.py
texsmith/adapters/latex/utils.py
texsmith/adapters/latex/engines/__init__.py
texsmith/adapters/latex/engines/latex/__init__.py
texsmith/adapters/latex/engines/latex/log.py
texsmith/adapters/latex/engines/latex/runner.py
texsmith/adapters/latex/engines/tectonic/__init__.py
texsmith/adapters/latex/partials/acronym.tex
texsmith/adapters/latex/partials/add.tex
texsmith/adapters/latex/partials/addition.tex
texsmith/adapters/latex/partials/blockquote.tex
texsmith/adapters/latex/partials/callout.tex
texsmith/adapters/latex/partials/choices.tex
texsmith/adapters/latex/partials/citation.tex
texsmith/adapters/latex/partials/codeblock.tex
texsmith/adapters/latex/partials/codeblock_listings.tex
texsmith/adapters/latex/partials/codeblock_pygments.tex
texsmith/adapters/latex/partials/codeblock_verbatim.tex
texsmith/adapters/latex/partials/codeinline.tex
texsmith/adapters/latex/partials/codeinlinett.tex
texsmith/adapters/latex/partials/comment.tex
texsmith/adapters/latex/partials/del.tex
texsmith/adapters/latex/partials/deletion.tex
texsmith/adapters/latex/partials/description_list.tex
texsmith-0.2.1.dist-info/METADATA
texsmith-0.2.1.dist-info/WHEEL
texsmith-0.2.1.dist-info/entry_points.txt
texsmith-0.2.1.dist-info/licenses/LICENSE.md
texsmith-0.2.1.dist-info/RECORD
