Metadata-Version: 2.4
Name: texsmith
Version: 0.2.1
Summary: A Markdown to LaTeX converter.
Project-URL: Homepage, https://github.com/yves-chevallier/texsmith
Author-email: Yves Chevallier <yves.chevalier@heig-vd.ch>
License-Expression: MIT
License-File: LICENSE.md
Keywords: convert,extensions,latex,markdown,mkdocs
Classifier: Programming Language :: Python :: 3
Classifier: Programming Language :: Python :: 3 :: Only
Classifier: Programming Language :: Python :: 3.10
Classifier: Programming Language :: Python :: 3.11
Classifier: Programming Language :: Python :: 3.12
Classifier: Programming Language :: Python :: 3.13
Classifier: Programming Language :: Python :: 3.14
Requires-Python: >=3.10
Requires-Dist: beautifulsoup4>=4.14.2
Requires-Dist: cairosvg>=2.8.2
Requires-Dist: emoji>=2.12.1
Requires-Dist: jinja2>=3.1.6
Requires-Dist: markdown>=3.7
Requires-Dist: pillow>=12.0.0
Requires-Dist: pint>=0.24
Requires-Dist: playwright>=1.56.0
Requires-Dist: pybtex>=0.24.0
Requires-Dist: pydantic>=2.7.0
Requires-Dist: pygments>=2.18.0
Requires-Dist: pylatexenc>=2.10
Requires-Dist: pymdown-extensions>=10.9
Requires-Dist: pymupdf>=1.24.3
Requires-Dist: pypdf>=6.1.1
Requires-Dist: python-markdown-math>=0.9
Requires-Dist: python-slugify>=8.0.4
Requires-Dist: pyxindy>=0.0.6
Requires-Dist: pyyaml>=6.0.3
Requires-Dist: requests>=2.32.5
Requires-Dist: rich>=13.9.0
Requires-Dist: tomli>=2.0.1; python_version < '3.11'
Requires-Dist: typer>=0.12.5
Requires-Dist: unicodeblocks>=0.3
